{
  "aliases": [
    "White Queen",
    "Adrienne Frost"
  ],
  "authors": [
    "Jay Faerber",
    "Terry Dodson."
  ],
  "description": "Adrienne Frost is a fictional character of the Marvel Universe, the older sister of Emma Frost and Cordelia Frost.",
  "images": {
    "background": null,
    "banner": null,
    "thumbnail": "https://upload.wikimedia.org/wikipedia/en/4/4b/Adriennefrost.jpg"
  },
  "isHero": false,
  "isVillain": false,
  "mainColor": null,
  "name": "White Queen (Adrienne Frost)",
  "partners": [
  ],
  "powers": [
    "Psychometry (paranormal)"
  ],
  "ranking": {
    "comicCount": 0,
    "eventCount": 0,
    "pageviewCount": 1911,
    "pageviewRank": -1,
    "serieCount": 0,
    "storyCount": 0
  },
  "secretIdentities": [
  ],
  "species": [
    "Mutant"
  ],
  "teams": [
    "Hellfire Club",
    "Generation X"
  ],
  "urls": {
    "marvel": "http://marvel.com/characters/2556/white_queen",
    "wikipedia": "https://en.wikipedia.org/wiki/Adrienne_Frost"
  }
}