{
  "aliases": [
    "Aftershock",
    "Allison Dillon",
    "Electra"
  ],
  "authors": [
    "Casey Jones",
    "Sean McKeever"
  ],
  "description": "Aftershock (Allison Dillon) is a fictional character, a supervillain that appears in the Marvel Comics' Spider-Girl series.",
  "images": {
    "thumbnail": "https://upload.wikimedia.org/wikipedia/en/e/ea/MC2Aftershock.jpg"
  },
  "isHero": null,
  "isVillain": null,
  "mainColor": null,
  "name": "Aftershock",
  "partners": [
    "Electro"
  ],
  "powers": [
    "Electric",
    "Electric manipulation",
    "Force field generation",
    "Magnetic levitation",
    "Manipulation"
  ],
  "ranking": {
    "comicCount": 0,
    "eventCount": 0,
    "pageviewCount": 46,
    "pageviewRank": -1,
    "serieCount": 0,
    "storyCount": 0
  },
  "secretIdentities": [
    "Allison Dillon"
  ],
  "species": [
  ],
  "teams": [
  ],
  "urls": {
    "wikipedia": "https://en.wikipedia.org/wiki/Aftershock_(comics)"
  }
}