{
  "name": "Annihilus",
  "url": "https://en.wikipedia.org/wiki/Annihilus",
  "realName": "",
  "creators": [
    "Stan Lee",
    "Jack Kirby"
  ],
  "teams": [
    "Annihilation Wave"
  ],
  "aliases": "Lord of the Negative Zone, the Living Death that Walks, Ahmyor",
  "species": [],
  "partners": [
    "Blastaar"
  ],
  "powers": [],
  "powersText": "Superhuman strength, stamina and durability<br>Flight<br>Wields Cosmic Control Rod:<br> Energy and molecular manipulation Slowed aging process }}"
}
