{
  "name": "Azazel",
  "url": "https://en.wikipedia.org/wiki/Azazel_(Marvel_Comics)",
  "realName": "Azazel",
  "creators": [
    "Chuck Austen",
    "Sean Phillips"
  ],
  "teams": [
    "Neyaphem"
  ],
  "aliases": "Satan <br> Beelzebub <br> Beliar <br> Gadreel",
  "species": [
    "Demonic Humanoid Mutant"
  ],
  "partners": [],
  "powers": [
    "Shapeshifting",
    "Dark Arts"
  ],
  "powersText": [
    "Teleportation",
    "Energy Blasts",
    "Shapeshifting",
    "Superhuman Agility",
    "Night Vision",
    "Healing Factor",
    "Immortality",
    "Telepathy",
    "Hypnosis",
    "Master Swordsman",
    "Master of Dark Arts"
  ],
  "image": {
    "url": "https://upload.wikimedia.org/wikipedia/en/thumb/f/f5/Azazel_HCV.jpg/200px-Azazel_HCV.jpg",
    "width": "200",
    "height": "330"
  },
  "pageviews": 24356
}
