{
  "name": "Battlestar",
  "url": "https://en.wikipedia.org/wiki/Battlestar_(comics)",
  "realName": "Lemar Hoskins",
  "creators": [
    "Mark Gruenwald",
    "Paul Neary"
  ],
  "teams": [
    "CSA",
    "Wild Pack"
  ],
  "aliases": "Bucky",
  "species": [],
  "partners": [
    "U.S. Agent"
  ],
  "powers": [
    "adamantium"
  ],
  "powersText": "Superhuman strength, stamina, durability, agility and reflexes<br>Highly trained acrobat and gymnast<br>Wields a near indestructible adamantium shield",
  "image": {
    "url": "https://upload.wikimedia.org/wikipedia/en/7/78/Battlestarm0.png",
    "width": "225",
    "height": "520"
  },
  "pageviews": 2172
}
