{
  "name": "Bill Foster",
  "url": "https://en.wikipedia.org/wiki/Bill_Foster_(comics)",
  "realName": "Dr. William Barrett \"Bill\" Foster",
  "creators": [
    "Stan Lee",
    "Don Heck"
  ],
  "teams": [
    "Centers for Disease Control",
    "Project: Pegasus",
    "Defenders",
    "Champions"
  ],
  "aliases": "Black Goliath, Giant-Man Goliath , Rockwell Dodsworth",
  "species": [],
  "partners": [],
  "powers": [],
  "powersText": "Brilliant biochemist<br>Gifted intellect<br>Superhuman strength<br>Size and mass manipulation",
  "image": {
    "url": "https://upload.wikimedia.org/wikipedia/en/7/77/GoliathWiki.jpg",
    "width": "200",
    "height": "303"
  },
  "pageviews": 32204
}
