{
  "aliases": [
  ],
  "alliances": [
  ],
  "authors": [
    "Fabian Nicieza",
    "Joe Madureira"
  ],
  "description": "Black Box (Garabed Bashur), formerly known as Commcast, is a fictional character in the Marvel Comics universe. He is a mutant and sometimes acts as a supervillain. He first appeared as Bashur in Deadpool: The Circle Chase #2, first appeared as Commcast in #3, and first appeared as Black Box in Cable & Deadpool #13.",
  "isHero": false,
  "isVillain": false,
  "name": "Black Box",
  "partners": [
  ],
  "powers": [
  ],
  "ranking": {
    "comicCount": 0,
    "eventCount": 0,
    "pageviewCount": 1226,
    "pageviewRank": -1,
    "serieCount": 0,
    "storyCount": 0
  },
  "secretIdentities": [
    "Garabed \"Gareb\" Bashur"
  ],
  "species": [
    "Mutant"
  ],
  "urls": {
    "wikipedia": "https://en.wikipedia.org/wiki/Black_Box_(comics)"
  }
}