{
  "aliases": [
    "Executioner",
    "Bloodaxe"
  ],
  "authors": [
    "Tom DeFalco",
    "Pat Olliffe"
  ],
  "description": "Bloodaxe (Jackie Lukus) is a fictional character, owned by Marvel Comics who exists in that company's Marvel Universe as a foe of Thor and Thunderstrike",
  "image": "https://upload.wikimedia.org/wikipedia/en/thumb/1/16/Bloodaxe.jpg/250px-Bloodaxe.jpg",
  "isHero": false,
  "isVillain": false,
  "name": "Bloodaxe",
  "partners": [
  ],
  "powers": [
    "Wields enchanted",
    "virtually indestructible axe that can cut through nearly anything",
    "project fire or ice energy",
    "bolts of Asgardian mystical force",
    "hurricane winds",
    "deflect bullets",
    "create dimensional rifts",
    "teleport to previous places",
    "Superhuman strength",
    "speed",
    "durability",
    "reflexes",
    "endurance",
    "Invulnerability to conventional firearms",
    "incendiary or ballistic devices",
    "virtually indestructible axe"
  ],
  "ranking": {
    "comicCount": 5,
    "eventCount": 0,
    "pageviewCount": 933,
    "pageviewRank": -1,
    "serieCount": 1,
    "storyCount": 6
  },
  "secretIdentities": [
    "Jackie Lukus"
  ],
  "species": [
  ],
  "teams": [
  ],
  "urls": {
    "marvel": "http://marvel.com/characters/316/bloodaxe",
    "wikipedia": "https://en.wikipedia.org/wiki/Bloodaxe_(comics)"
  }
}