{
  "aliases": [
    "Cloak",
    "Dagger"
  ],
  "authors": [
    "Bill Mantlo",
    "Ed Hannigan"
  ],
  "description": "Cloak (Tyrone \"Ty\" Johnson) and Dagger (Tandy Bowen) are a fictional comic book superhero duo in Marvel Universe.",
  "images": {
    "background": null,
    "banner": null,
    "thumbnail": "http://i.annihil.us/u/prod/marvel/i/mg/5/e0/528d31d76a2b0/standard_xlarge.jpg"
  },
  "isHero": null,
  "isVillain": null,
  "mainColor": null,
  "name": "Cloak",
  "partners": [
  ],
  "powers": [
    "Teleportation",
    "Intangibility",
    "Daggers",
    "Darkforce"
  ],
  "ranking": {
    "comicCount": 33,
    "eventCount": 3,
    "pageviewCount": 19126,
    "pageviewRank": -1,
    "serieCount": 18,
    "storyCount": 36
  },
  "secretIdentities": [
    "Tyrone Johnson",
    "Tandy Bowen",
    "Ty"
  ],
  "species": [
    "Mutate"
  ],
  "teams": [
    "Defenders",
    "Brides of Set",
    "X-Men",
    "Dark X-Men",
    "Civil War",
    "New Warriors",
    "Runaways",
    "Marvel Knights",
    "Secret Avengers (Civil War)",
    "''(Dagger)''",
    "Secret Defenders",
    "Brides of Set ''(Dagger)''"
  ],
  "urls": {
    "marvel": "http://marvel.com/comics/characters/1009241/cloak",
    "wikipedia": "https://en.wikipedia.org/wiki/Cloak_and_Dagger_(comics)"
  }
}