{
  "aliases": [
    "Coachwhip"
  ],
  "authors": [
    "Mark Gruenwald",
    "Kieron Dwyer"
  ],
  "description": "Coachwhip is a fictional character.",
  "images": {
    "thumbnail": "https://upload.wikimedia.org/wikipedia/en/4/41/Coachwhip1.jpg"
  },
  "isHero": null,
  "isVillain": null,
  "mainColor": null,
  "name": "Coachwhip",
  "partners": [
  ],
  "powers": [
  ],
  "ranking": {
    "comicCount": 0,
    "eventCount": 0,
    "pageviewCount": 542,
    "pageviewRank": -1,
    "serieCount": 0,
    "storyCount": 0
  },
  "secretIdentities": [
    "Beatrix Keener"
  ],
  "species": [
  ],
  "teams": [
    "Serpent Society"
  ],
  "urls": {
    "wikipedia": "https://en.wikipedia.org/wiki/Coachwhip_(comics)"
  }
}