{
  "name": "Count Nefaria",
  "url": "https://en.wikipedia.org/wiki/Count_Nefaria",
  "realName": "Luchino Nefaria",
  "creators": [
    "Stan Lee",
    "Don Heck"
  ],
  "teams": [
    "Maggia",
    "Legion of the Unliving",
    "Death Squad",
    "Lethal Legion",
    "Ani-Men"
  ],
  "aliases": "The Dream Master",
  "species": [],
  "partners": [],
  "powers": [],
  "powersText": "Superhuman strength, speed, stamina, agility, reflexes, durability, healing and longevity<br> Optic blasts Flight }}",
  "image": {
    "url": "https://upload.wikimedia.org/wikipedia/en/f/fe/Avengers166.jpg",
    "width": "250",
    "height": "373"
  },
  "pageviews": 7198
}
