{
  "name": "Dead Girl",
  "url": "https://en.wikipedia.org/wiki/Dead_Girl",
  "realName": "Moonbeam (surname unrevealed)",
  "creators": [
    "Peter Milligan",
    "Mike Allred"
  ],
  "teams": [
    "X-Statix",
    "X-Force"
  ],
  "aliases": "",
  "species": [
    "Human Mutant"
  ],
  "partners": [],
  "powers": [],
  "powersText": "Acclerated healing factor,<br>Telepathy with the dead,<br>Superhuman strength, speed, agility, reflexes<br>Intangibility",
  "image": {
    "url": "https://upload.wikimedia.org/wikipedia/en/thumb/9/99/Question_book-new.svg/50px-Question_book-new.svg.png",
    "width": "50",
    "height": "39"
  },
  "pageviews": 1926
}
