{
  "aliases": [
    "War",
    "Deathbird"
  ],
  "authors": [
    "Chris Claremont",
    "Dave Cockrum"
  ],
  "description": "Deathbird (Cal'syee Neramani-Summers) is a fictional character",
  "image": "http://i.annihil.us/u/prod/marvel/i/mg/2/60/4c004041be770/standard_xlarge.jpg",
  "isHero": false,
  "isVillain": true,
  "name": "Deathbird",
  "partners": [
  ],
  "powers": [
    "Natural wings",
    "Superhuman strength",
    "stamina",
    "sturdiness",
    "Razor-sharp talons"
  ],
  "ranking": {
    "comicCount": 26,
    "eventCount": 2,
    "pageviewCount": 4961,
    "pageviewRank": -1,
    "serieCount": 9,
    "storyCount": 30
  },
  "secretIdentities": [
    "Cal'syee Neramani-Summers"
  ],
  "species": [
  ],
  "teams": [
    "Starforce",
    "Horsemen of Apocalypse",
    "Shi'ar",
    "Brood",
    "Shi'ar Imperium",
    "The Brood"
  ],
  "urls": {
    "marvel": "http://marvel.com/characters/525/deathbird",
    "wikipedia": "https://en.wikipedia.org/wiki/Deathbird"
  }
}