{
  "aliases": [
  ],
  "alliances": [
    "Infinity Watch",
    "Guardians of the Galaxy (2008 team)",
    "Annihilation",
    "Phalanx"
  ],
  "authors": [
    "Jim Starlin"
  ],
  "description": "Gamora is a fictional character, an antiheroine that appears in comic books published by Marvel Comics. Created by Jim Starlin, the character first appeared in Strange Tales #180 (June 1975). Gamora is the adopted daughter of the supervillain Thanos, and the last of her species. Her powers include superhuman strength and agility and an accelerated healing factor. She has appeared as the occasional love interest of the superheroes Adam Warlock and Nova, and a member of the group known as the Infinity Watch.The character played a role in the 2007 crossover comic book event Annihilation: Conquest, and became a member of the titular team in its spin-off comic, Guardians of the Galaxy. She has been featured in a variety of associated Marvel merchandise. Zoe Saldana plays the character in the 2014 live-action film Guardians of the Galaxy.",
  "image": "http://i.annihil.us/u/prod/marvel/i/mg/5/90/526032a2cce62/standard_xlarge.jpg",
  "isHero": false,
  "isVillain": false,
  "name": "Gamora",
  "partners": [
  ],
  "powers": [
    "Accelerated healing factor",
    "Highly skilled assassin",
    "gymnast",
    "Superhuman strength",
    "speed",
    "agility",
    "durability",
    "Skilled martial artist"
  ],
  "ranking": {
    "comicCount": 10,
    "eventCount": 3,
    "pageviewCount": 25626,
    "pageviewRank": -1,
    "serieCount": 5,
    "storyCount": 10
  },
  "secretIdentities": [
    "Gamora"
  ],
  "species": [
    "Zen Whoberi"
  ],
  "urls": {
    "marvel": "http://marvel.com/characters/20/gamora",
    "wikipedia": "https://en.wikipedia.org/wiki/Gamora"
  }
}