{
  "aliases": [
    "Gauntlet",
    "Joseph Green"
  ],
  "authors": [
    "Dan Slott",
    "Eric Powell",
    "Stefano Caselli"
  ],
  "description": "The Gauntlet (Joseph Green), is a comic book superhero in the Marvel Comics Universe.",
  "images": {
    "background": null,
    "banner": null,
    "thumbnail": "http://i.annihil.us/u/prod/marvel/i/mg/7/20/535ff2a48869b/standard_xlarge.jpg"
  },
  "isHero": null,
  "isVillain": null,
  "mainColor": null,
  "name": "Gauntlet (Joseph Green)",
  "partners": [
  ],
  "powers": [
    "Hand",
    "Right hand controls large"
  ],
  "ranking": {
    "comicCount": 25,
    "eventCount": 4,
    "pageviewCount": 59,
    "pageviewRank": -1,
    "serieCount": 9,
    "storyCount": 27
  },
  "secretIdentities": [
    "Joseph Green"
  ],
  "species": [
  ],
  "teams": [
    "Avengers Resistance",
    "Counter Force",
    "Fifty State Initiative",
    "New Warriors",
    "The Initiative",
    "United States Army"
  ],
  "urls": {
    "marvel": "http://marvel.com/comics/characters/1009316/gauntlet_joseph_green",
    "wikipedia": "https://en.wikipedia.org/wiki/Gauntlet_(comics)"
  }
}