{
  "name": "Grandmaster",
  "url": "https://en.wikipedia.org/wiki/Grandmaster_(Marvel_Comics)",
  "realName": "En Dwi Gast",
  "creators": [
    "Roy Thomas",
    "John Buscema"
  ],
  "teams": [
    "Squadron Sinister",
    "Elders of the Universe"
  ],
  "aliases": "The Master of Games",
  "species": [],
  "partners": [],
  "powers": [
    "Power Primordial"
  ],
  "powersText": [
    "User of the Power Primordial:",
    "Immortality",
    "Master of all games",
    "Master strategist and tactician",
    "Energy control",
    "Size and matter manipulation",
    "Ability to \"will\" the death and resurrection of another"
  ],
  "image": {},
  "pageviews": 14317
}
