{
  "name": "Grey Gargoyle",
  "url": "https://en.wikipedia.org/wiki/Grey_Gargoyle",
  "realName": "Paul Pierre Duval",
  "creators": [
    "Stan Lee",
    "Jack Kirby"
  ],
  "teams": [
    "Masters of Evil",
    "AIM",
    "The Worthy",
    "Lethal Legion",
    "Hood"
  ],
  "aliases": "Paul St. Pierre, Mokk: Breaker of Faith",
  "species": [],
  "partners": [],
  "powers": [],
  "powersText": [
    "Genius chemist",
    "Superhuman strength and durability",
    "Ability to turn creatures and objects to stone via physical contact"
  ],
  "image": {
    "url": "https://upload.wikimedia.org/wikipedia/en/thumb/0/0b/Journey_into_Mystery_107.jpg/250px-Journey_into_Mystery_107.jpg",
    "width": "250",
    "height": "376"
  },
  "pageviews": 3783
}
