{
  "aliases": [
    "The Hood",
    "Hood"
  ],
  "authors": [
    "Eric Powell",
    "Brian K. Vaughan",
    "Kyle Hotz"
  ],
  "description": "The Hood (real name Parker Robbins) is a fictional character, a supervillain, and a crime boss in the Marvel Comics Universe",
  "image": "http://i.annihil.us/u/prod/marvel/i/mg/6/90/539a09a2863cf/standard_xlarge.jpg",
  "isHero": false,
  "isVillain": false,
  "name": "The Hood",
  "partners": [
  ],
  "powers": [
    "Infinity Gems",
    "criminal mastermind",
    "marksman",
    "Formerly: reality manipulation using the Norn Stones",
    "magical cloak",
    "boots for invisibility",
    "air walking",
    "demon transformation",
    "marksman Formerly: reality manipulation using the Norn Stones"
  ],
  "ranking": {
    "comicCount": 0,
    "eventCount": 0,
    "pageviewCount": 9848,
    "pageviewRank": -1,
    "serieCount": 0,
    "storyCount": 0
  },
  "secretIdentities": [
    "Parker Robbins"
  ],
  "species": [
  ],
  "teams": [
    "Avengers: The Initiative",
    "Cabal",
    "The Cabal",
    "The Initiative",
    "Illuminati"
  ],
  "urls": {
    "marvel": "http://marvel.com/comics/characters/1010715/the_hood",
    "wikipedia": "https://en.wikipedia.org/wiki/Hood_(comics)"
  }
}