{
  "aliases": "",
  "creators": [
    "Mark Gruenwald",
    "Paul Ryan",
    "J. Michael Straczynski",
    "Gary Frank"
  ],
  "image": {
  },
  "name": "Inertia",
  "pageviews": 1381,
  "partners": [
  ],
  "powers": [
    "kinetic energy"
  ],
  "powersText": [
    "transfer kinetic energy into object or person"
  ],
  "realName": "Edith ''Eddy'' Freiberg",
  "species": [
  ],
  "teams": [
    "America Redeemers",
    "Squadron Supreme",
    "The Squadron Supreme"
  ],
  "url": "https://en.wikipedia.org/wiki/Inertia_(Marvel_Comics)"
}