{
  "name": "Jason Macendale, Jr.",
  "url": "https://en.wikipedia.org/wiki/Jason_Macendale",
  "realName": "Jason Philip Macendale, Jr.",
  "creators": [
    "Tom DeFalco",
    "Steve Ditko"
  ],
  "teams": [
    "Sinister Six"
  ],
  "aliases": "Jack O'Lantern Hobgoblin",
  "species": [],
  "partners": [
    "Gaunt"
  ],
  "powers": [
    "Kraven",
    "cybernetic"
  ],
  "powersText": "Highly trained hand to hand combatant, martial artist and spy<br>Expert mechanical engineer and physicists<br>Superhuman physical abilities due to Kraven 's formula and cybernetic implants<br>Use of various goblin-themed weapons and paraphernalia<br>(When possessed by demon):<br>Superhuman strength, speed and agility<br>Hellfire powers<br>Ability to create organic fibers",
  "image": {
    "url": "https://upload.wikimedia.org/wikipedia/en/thumb/a/a4/Webofspiderman93panel.jpg/250px-Webofspiderman93panel.jpg",
    "width": "250",
    "height": "291"
  },
  "pageviews": 3608
}
