{
  "name": "Joseph",
  "url": "https://en.wikipedia.org/wiki/Joseph_(comics)",
  "realName": "Joseph",
  "creators": [
    "Scott Lobdell",
    "Roger Cruz",
    "Magneto",
    "Stan Lee",
    "Jack Kirby"
  ],
  "teams": [
    "X-Men",
    "Acolytes",
    "Brotherhood of Evil Mutants"
  ],
  "aliases": "Magneto",
  "species": [
    "Human Mutant"
  ],
  "partners": [],
  "powers": [],
  "powersText": [
    "Generation and manipulation of magnetic fields"
  ],
  "image": {
    "url": "https://upload.wikimedia.org/wikipedia/en/thumb/b/ba/Joseph_%28Magneto%27s_Clone%29.jpg/225px-Joseph_%28Magneto%27s_Clone%29.jpg",
    "width": "225",
    "height": "153"
  },
  "pageviews": 2411
}
