{
  "aliases": [
    "Malice",
    "Omega Sentinel",
    "Karima Shapandar"
  ],
  "authors": [
    "Brett Booth",
    "Chris Claremont"
  ],
  "description": "Omega Sentinel (Karima Shapandar) is a fictional character associated with the X-Men and its spinoff Excalibur.",
  "images": {
    "background": null,
    "banner": null,
    "thumbnail": "http://i.annihil.us/u/prod/marvel/i/mg/8/70/4c002e4dc5f11/standard_xlarge.jpg"
  },
  "isHero": null,
  "isVillain": null,
  "mainColor": null,
  "name": "Omega Sentinel",
  "partners": [
  ],
  "powers": [
    "Flight",
    "As a prime sentinel",
    "Superhuman strength",
    "Resistance to injury",
    "Regenerative abilities",
    "As a prime sentinel;"
  ],
  "ranking": {
    "comicCount": 0,
    "eventCount": 0,
    "pageviewCount": 3598,
    "pageviewRank": -1,
    "serieCount": 0,
    "storyCount": 0
  },
  "secretIdentities": [
    "Karima Shapandar"
  ],
  "species": [
  ],
  "teams": [
    "Prime Sentinel",
    "Excalibur",
    "Marauders",
    "X-Men",
    "Acolytes",
    "Genoshan Excalibur",
    "Omega Prime Sentinels"
  ],
  "urls": {
    "marvel": "http://marvel.com/characters/1653/omega_sentinel",
    "wikipedia": "https://en.wikipedia.org/wiki/Karima_Shapandar"
  }
}