{
  "aliases": "Vincent Colorito, Frog-Face, Frog-Man",
  "creators": [
    "Stan Lee",
    "Gene Colan",
    "Frank Giacoia"
  ],
  "image": {
  },
  "name": "Leap-Frog",
  "pageviews": 1978,
  "partners": [
  ],
  "powers": [
  ],
  "powersText": [
    "Exoskeleton frog suit grants:",
    "Enhanced strength and agility",
    "Internal padding for impacts",
    "Computer-guided system for leaping accuracy",
    "Ability to leap great distances"
  ],
  "realName": null,
  "species": [
  ],
  "teams": [
    "Defenders Impersonators",
    "Emissaries of Evil",
    "Damage Control"
  ],
  "url": "https://en.wikipedia.org/wiki/Leap-Frog_(comics)"
}