{
  "aliases": [
    "Magician"
  ],
  "alliances": [
    "Ultimate X-Men"
  ],
  "authors": [
    "Robert Kirkman",
    "Tom Raney",
    "Stan Lee",
    "Dick Ayers"
  ],
  "description": "Magician (Elliot Boggs) is a fictional character in the Ultimate Marvel imprint of Marvel Comics. Created by Robert Kirkman, he first appears in Ultimate X-Men #66. Magician is one of the few Ultimate Marvel characters who are not based on counterparts from the Marvel Universe.",
  "image": "https://upload.wikimedia.org/wikipedia/en/4/4f/XMEN_Magician.jpg",
  "isHero": false,
  "isVillain": false,
  "name": "Magician",
  "partners": [
  ],
  "powers": [
  ],
  "ranking": {
    "comicCount": 0,
    "eventCount": 0,
    "pageviewCount": 1207,
    "pageviewRank": -1,
    "serieCount": 0,
    "storyCount": 0
  },
  "secretIdentities": [
    "Elliot Boggs",
    "Lee Guardineer"
  ],
  "species": [
  ],
  "urls": {
    "wikipedia": "https://en.wikipedia.org/wiki/Magician_(comics)"
  }
}