{
  "aliases": "Magnus,",
  "creators": [
    "Stan Lee",
    "Jack Kirby"
  ],
  "image": {
    "height": "353",
    "url": "https://upload.wikimedia.org/wikipedia/en/thumb/4/4a/MagnetoYardin.png/250px-MagnetoYardin.png",
    "width": "250"
  },
  "marvel": {
    "counts": {
      "comics": 248,
      "events": 15,
      "series": 110,
      "stories": 247
    },
    "description": "",
    "id": 1009417,
    "image": "http://i.annihil.us/u/prod/marvel/i/mg/3/b0/5261a7e53f827.jpg",
    "url": "http://marvel.com/universe/Magneto_(Max_Eisenhardt)"
  },
  "name": "Magneto",
  "pageviews": 76623,
  "partners": [
  ],
  "powers": [
    "Magnetism"
  ],
  "powersText": [
    "Magnetism manipulation and generation of magnetic force fields",
    "Flight through magnetic fields",
    "Helmet shields against telepathic attacks"
  ],
  "realName": "Max Eisenhardt",
  "species": [
    "Human Mutant"
  ],
  "teams": [
    "Brotherhood of Evil Mutants",
    "Genoshan Excalibur",
    "X-Men",
    "New Mutants",
    "The Twelve",
    "Hellfire Club",
    "Acolytes",
    "Savage Land Mutates",
    "Astonishing Avengers"
  ],
  "url": "https://en.wikipedia.org/wiki/Magneto_(comics)"
}