{
  "aliases": [
    "Rex Carpenter",
    "Hate-Monger",
    "Super-Beast",
    "Man-Beast",
    "Hate Monger"
  ],
  "authors": [
    "Stan Lee",
    "Jack Kirby"
  ],
  "description": "The Man-Beast is a fictional character who appears in the comic books published by Marvel Comics.",
  "images": {
    "background": null,
    "banner": null,
    "thumbnail": "http://i.annihil.us/u/prod/marvel/i/mg/5/50/4c0035ea3151e/standard_xlarge.jpg"
  },
  "isHero": false,
  "isVillain": false,
  "mainColor": null,
  "name": "Hate-Monger (Adolf Hitler)",
  "partners": [
    "Exodus"
  ],
  "powers": [
    "Ultraviolet range of the light spectrum",
    "Superhuman strength",
    "Speed",
    "Durability",
    "Intelligence",
    "Use of technological weapons",
    "Gadgets",
    "Enhanced senses",
    "Superior hand to hand combatant",
    "Psychic powers"
  ],
  "ranking": {
    "comicCount": 2,
    "eventCount": 0,
    "pageviewCount": 1625,
    "pageviewRank": -1,
    "serieCount": 2,
    "storyCount": 2
  },
  "secretIdentities": [
  ],
  "species": [
    "Uplifted red wolf"
  ],
  "teams": [
    "New Men",
    "Legion of Light",
    "United Nations"
  ],
  "urls": {
    "marvel": "http://marvel.com/characters/913/hate-monger",
    "wikipedia": "https://en.wikipedia.org/wiki/Man-Beast"
  }
}