{
  "aliases": [
    "Master Menace",
    "Emil Burbank"
  ],
  "authors": [
    "J. Michael Straczynski",
    "Roy Thomas",
    "Wayne Boring"
  ],
  "description": "Dr. Emil Burbank, also known as Master Menace, is a fictional Marvel Comics character.",
  "isHero": false,
  "isVillain": false,
  "name": "Master Menace",
  "partners": [
  ],
  "powers": [
    "Superhuman intelligence",
    "Various weapons",
    "Genius level inventor",
    "Powered exoskeleton",
    "Genius level",
    "Inventor",
    "Powered armor"
  ],
  "ranking": {
    "comicCount": 0,
    "eventCount": 0,
    "pageviewCount": 559,
    "pageviewRank": -1,
    "serieCount": 0,
    "storyCount": 0
  },
  "secretIdentities": [
    "Emil Zebediah Burbank"
  ],
  "species": [
  ],
  "teams": [
    "Squadron Supreme",
    "Redeemers",
    "Squadron Supreme (Supreme Power)",
    "America Redeemers"
  ],
  "urls": {
    "wikipedia": "https://en.wikipedia.org/wiki/Master_Menace"
  }
}