{
  "aliases": [
    "Think Tank",
    "Mentallo"
  ],
  "authors": [
    "Stan Lee",
    "Jack Kirby"
  ],
  "description": "Mentallo (Marvin Flumm) is a fictional comic book supervillain, a mutant who appears in books published by Marvel Comics.After having been fired for cause after attempting a covert S.H.I.E.L.D. takeover, he has since operated as both a freelance criminal and subversive and a high-ranking agent of HYDRA.",
  "images": {
    "background": null,
    "banner": null,
    "thumbnail": "http://i.annihil.us/u/prod/marvel/i/mg/2/c0/4c0030b9256c6/standard_xlarge.jpg"
  },
  "isHero": null,
  "isVillain": null,
  "mainColor": null,
  "name": "Mentallo",
  "partners": [
    "Fixer"
  ],
  "powers": [
    "Telepathy",
    "Radar"
  ],
  "ranking": {
    "comicCount": 1,
    "eventCount": 0,
    "pageviewCount": 1491,
    "pageviewRank": -1,
    "serieCount": 1,
    "storyCount": 1
  },
  "secretIdentities": [
    "Marvin Flumm"
  ],
  "species": [
    "Mutant"
  ],
  "teams": [
    "Resistants",
    "Advanced Idea Mechanics",
    "Hydra",
    "S.H.I.E.L.D",
    "New Enforcers",
    "A.I.M"
  ],
  "urls": {
    "marvel": "http://marvel.com/characters/1424/mentallo",
    "wikipedia": "https://en.wikipedia.org/wiki/Mentallo"
  }
}