{
  "aliases": "",
  "creators": [
    "Joss Whedon",
    "John Cassaday"
  ],
  "image": {
    "height": "291",
    "url": "https://upload.wikimedia.org/wikipedia/en/thumb/e/ee/Ord_of_the_Breakworld.jpg/250px-Ord_of_the_Breakworld.jpg",
    "width": "250"
  },
  "name": "Ord of the Breakworld",
  "pageviews": 1393,
  "partners": [
  ],
  "powers": [
  ],
  "powersText": [
    "Superhuman strength speed and endurance",
    "Enhanced durability",
    "Enhanced hearing",
    "Flight",
    "Master martial artist",
    "Highly skilled in use of bladed weapons"
  ],
  "realName": "Ord",
  "species": [
  ],
  "teams": [
  ],
  "url": "https://en.wikipedia.org/wiki/Ord_(comics)"
}