{
  "aliases": [
    "Omertà",
    "Paulie Provenzano"
  ],
  "authors": [
    "Salvador Larroca",
    "Scott Lobdell"
  ],
  "description": "Omertà (Paul \"Paulie\" Provenzano) is a fictional character, a mutant in the Marvel Universe.",
  "image": "https://upload.wikimedia.org/wikipedia/en/d/d4/OmertaX-Men.JPG",
  "isHero": false,
  "isVillain": false,
  "name": "Omertà",
  "partners": [
  ],
  "powers": [
    "Superhuman strength",
    "Invulnerability"
  ],
  "ranking": {
    "comicCount": 0,
    "eventCount": 0,
    "pageviewCount": 198,
    "pageviewRank": -1,
    "serieCount": 0,
    "storyCount": 0
  },
  "secretIdentities": [
    "Paul Provenzano"
  ],
  "species": [
  ],
  "teams": [
    "United States Army",
    "Genoshan Assault X-Men"
  ],
  "urls": {
    "wikipedia": "https://en.wikipedia.org/wiki/Paulie_Provenzano"
  }
}