{
  "name": "Redneck",
  "url": "https://en.wikipedia.org/wiki/Redneck_(comics)",
  "realName": "Vincent \"Vin\" Stewart",
  "creators": [
    "Grant Morrison",
    "Frank Quitely"
  ],
  "teams": [
    "New Warriors",
    "Xavier Institute",
    "Omega Gang"
  ],
  "aliases": "Skybolt",
  "species": [],
  "partners": [],
  "powers": [
    "the Beetle"
  ],
  "powersText": "Uses weaponry and flight pack derived from the designs of  the Beetle <br>Depowered, formerly:<br>Heat generation",
  "image": {
    "url": "https://upload.wikimedia.org/wikipedia/en/thumb/6/67/Skybolt1.jpg/250px-Skybolt1.jpg",
    "width": "250",
    "height": "240"
  },
  "pageviews": 1353
}
