{
  "aliases": "",
  "creators": [
    "Jeph Loeb",
    "Simone Bianchi"
  ],
  "image": {
    "height": "391",
    "url": "https://upload.wikimedia.org/wikipedia/en/thumb/4/4b/RomulusWolverine.PNG/250px-RomulusWolverine.PNG",
    "width": "250"
  },
  "name": "Romulus",
  "pageviews": 4407,
  "partners": [
  ],
  "powers": [
  ],
  "powersText": [
    "Adamantium laced skeleton & claws",
    "Regenerative healing factor",
    "Superhuman senses",
    "strength",
    "stamina",
    "speed",
    "agility",
    "reflexes",
    "endurance & longevity",
    "Animalistic traits",
    "Telepathy",
    "Skilled combatant & strategist"
  ],
  "realName": null,
  "species": [
    "Human Mutant"
  ],
  "teams": [
    "Weapon X"
  ],
  "url": "https://en.wikipedia.org/wiki/Romulus_(comics)"
}