{
  "name": "The Russian",
  "url": "https://en.wikipedia.org/wiki/Russian_(comics)",
  "realName": "",
  "creators": [
    "Garth Ennis"
  ],
  "teams": [],
  "aliases": "The Ivan",
  "species": [
    "Cyborg"
  ],
  "partners": [],
  "powers": [],
  "powersText": "Considerable strength, stamina and durability<br>Nigh-invulnerability<br>Enhanced smell",
  "image": {
    "url": "https://upload.wikimedia.org/wikipedia/en/thumb/c/ce/Russian-assassin.jpg/250px-Russian-assassin.jpg",
    "width": "250",
    "height": "328"
  },
  "pageviews": 5915
}
