{
  "aliases": [
    "Tessa",
    "Lady Tessa",
    "Diana Fox",
    "Britannia",
    "Sage"
  ],
  "alliances": [
    "S.W.O.R.D.",
    "Excalibur",
    "X-Treme X-Men",
    "Hellfire Club",
    "X-Men",
    "Exiles",
    "X-Treme Sanctions Executive",
    "Multiverse X-Men",
    "New Excalibur",
    "The Hellfire Club"
  ],
  "authors": [
    "John Byrne",
    "Chris Claremont"
  ],
  "description": "Sage, also known as Tessa, is a fictional character in the Marvel Comics universe. She has most often been associated with the X-Men and the Hellfire Club, whom she spied upon for Professor Charles Xavier.A mutant, Sage possesses a number of mental abilities and was originally presented as the personal assistant to the Hellfire Club’s Sebastian Shaw, but an extended retcon revealed that she had been one of the first mutants discovered by Professor Xavier. She has been a member of the original X-Men teams, the X-Treme X-Men, Excalibur, the Exiles, and a cross-dimensional X-Men team similar to the Exiles known as the X-Treme X-Men.",
  "image": "http://i.annihil.us/u/prod/marvel/i/mg/5/90/4c003c44095cb/standard_xlarge.png",
  "isHero": false,
  "isVillain": false,
  "name": "Sage",
  "partners": [
  ],
  "powers": [
    "Ability to jumpstart mutant powers",
    "superhuman mental processing including perfect memory",
    "data analysis",
    "telepathy"
  ],
  "ranking": {
    "comicCount": 6,
    "eventCount": 0,
    "pageviewCount": 5364,
    "pageviewRank": -1,
    "serieCount": 6,
    "storyCount": 6
  },
  "secretIdentities": [
    "Tessa"
  ],
  "species": [
  ],
  "urls": {
    "marvel": "http://marvel.com/characters/1977/sage",
    "wikipedia": "https://en.wikipedia.org/wiki/Sage_(comics)"
  }
}