{
  "aliases": "",
  "creators": [
    "David Michelinie",
    "Mark Bagley"
  ],
  "image": {
    "height": "364",
    "url": "https://upload.wikimedia.org/wikipedia/en/thumb/e/e5/Sentry2.jpg/250px-Sentry2.jpg",
    "width": "250"
  },
  "name": "Sentry",
  "pageviews": 572,
  "partners": [
  ],
  "powers": [
  ],
  "powersText": [
    "No superhuman powers",
    "body-armor",
    "jet-boots",
    "repulsor gun"
  ],
  "realName": "Curtis Elkins",
  "species": [
  ],
  "teams": [
    "The Jury"
  ],
  "url": "https://en.wikipedia.org/wiki/Sentry_(Curtis_Elkins)"
}