{
  "name": "Sif",
  "url": "https://en.wikipedia.org/wiki/Sif_(comics)",
  "realName": null,
  "creators": [
    "Stan Lee",
    "Jack Kirby"
  ],
  "teams": [],
  "aliases": "Sylvan",
  "species": [
    "Asgardian"
  ],
  "partners": [],
  "powers": [
    "Superhuman strength",
    "endurance",
    "longevity"
  ],
  "powersText": [
    "Superhuman strengthendurance",
    "and longevity"
  ],
  "image": {
    "url": "https://upload.wikimedia.org/wikipedia/en/thumb/6/6b/Sif.jpg/250px-Sif.jpg",
    "width": "250",
    "height": "377"
  },
  "pageviews": 31021
}
