{
  "aliases": [
  ],
  "alliances": [
    "Desert Sword"
  ],
  "authors": [
    "Kirk Jarvinen",
    "Fabian Nicieza"
  ],
  "description": "Sirocco is a fictional character, a mutant in the Marvel Comics Universe. His first appearance was in New Mutants Annual #7.",
  "isHero": false,
  "isVillain": false,
  "name": "Sirocco",
  "partners": [
  ],
  "powers": [
    "Create funnels of air that can be used to pick things up or strike enemies with concussive force."
  ],
  "ranking": {
    "comicCount": 0,
    "eventCount": 0,
    "pageviewCount": 272,
    "pageviewRank": -1,
    "serieCount": 0,
    "storyCount": 0
  },
  "secretIdentities": [
  ],
  "species": [
    "Mutant"
  ],
  "urls": {
    "wikipedia": "https://en.wikipedia.org/wiki/Sirocco_(comics)"
  }
}