{
  "name": "Sleepwalker",
  "url": "https://en.wikipedia.org/wiki/Sleepwalker_(comics)",
  "realName": null,
  "creators": [
    "Bob Budiansky"
  ],
  "teams": [
    "S.H.I.E.L.D.",
    "Secret Defenders"
  ],
  "aliases": "Sleepy",
  "species": [],
  "partners": [],
  "powers": [],
  "powersText": [
    "Superhuman strength and durability",
    "enhanced agility",
    "reflexes",
    "running speed",
    "levitation",
    "and stamina.",
    "Superhuman visual acuity.",
    "Substance altering eyebeams.",
    "Immunity to sleep and other resistances due to alien physiology."
  ],
  "image": {
    "url": "https://upload.wikimedia.org/wikipedia/en/thumb/b/b5/Sleepwalker_%28Marvel_comics%29.jpg/250px-Sleepwalker_%28Marvel_comics%29.jpg",
    "width": "250",
    "height": "282"
  },
  "pageviews": 3135
}
