{
  "url": "https://en.wikipedia.org/wiki/Spider-Girl",
  "realName": "May \"Mayday\" Parker",
  "creators": [
    "Tom DeFalco",
    "Ron Frenz",
    "Mark Bagley"
  ],
  "teams": [
    "A-Next",
    "Fantastic Five",
    "New Warriors",
    "Web Warriors"
  ],
  "aliases": "Spidey, Spider-Girl Red",
  "species": [],
  "partners": [],
  "powers": [
    "Bio-magnetism"
  ],
  "powersText": "Ability to stick to solid surfaces and repel objects and people<br>Superhuman strength, durability, stamina, speed, agility, reflexes, and endurance<br>Precognitive \"Spider-Sense\"<br> Bio-magnetism manipulation<br>Ability to sense the weak points in her enemies",
  "image": {
    "url": "https://upload.wikimedia.org/wikipedia/en/thumb/2/2e/Spider-girl-continues.jpg/250px-Spider-girl-continues.jpg",
    "width": "250",
    "height": "377"
  },
  "pageviews": 22686
}
