{
  "aliases": "Bolt",
  "creators": [
    "Chris Claremont",
    "Dave Cockrum"
  ],
  "image": {
  },
  "marvel": {
    "counts": {
      "comics": 8,
      "events": 0,
      "series": 5,
      "stories": 5
    },
    "description": "Starbolt is a member of the Shi'ar Imperial Guard.",
    "id": 1009621,
    "image": "http://i.annihil.us/u/prod/marvel/i/mg/e/70/4c003acf4e4bc.jpg",
    "url": "http://marvel.com/universe/Starbolt"
  },
  "name": "Starbolt",
  "pageviews": 1215,
  "partners": [
  ],
  "powers": [
  ],
  "powersText": [
    "Fire immunity",
    "Generates high heated plasma",
    "Supersonic flight"
  ],
  "realName": null,
  "species": [
  ],
  "teams": [
    "Imperial Guard"
  ],
  "url": "https://en.wikipedia.org/wiki/Starbolt"
}