{
  "aliases": [
    "Nova Omega",
    "(Garthan Saal)",
    "Supernova"
  ],
  "alliances": [
    "Nova Corps"
  ],
  "authors": [
    "Tom DeFalco"
  ],
  "description": "Supernova, aka Nova Omega and (Garthan Saal), is a fictional character in Marvel Comics. He first appeared as an antagonist in Avengers vol 1 #301 in 1988.",
  "isHero": false,
  "isVillain": true,
  "name": "Supernova",
  "partners": [
  ],
  "powers": [
    "Gravametric manipulation"
  ],
  "ranking": {
    "comicCount": 0,
    "eventCount": 0,
    "pageviewCount": 2320,
    "pageviewRank": -1,
    "serieCount": 0,
    "storyCount": 0
  },
  "secretIdentities": [
    "Garthan Saal"
  ],
  "species": [
  ],
  "urls": {
    "wikipedia": "https://en.wikipedia.org/wiki/Supernova_(Marvel_Comics)"
  }
}