{
  "name": "Super-Adaptoid",
  "url": "https://en.wikipedia.org/wiki/Super-Adaptoid",
  "realName": "Super-Adaptoid",
  "creators": [
    "Stan Lee",
    "Gene Colan",
    "Jack Kirby"
  ],
  "teams": [
    "A.I.M.",
    "Heavy Metal",
    "Phalanx"
  ],
  "aliases": "Adaptoid, Alessandro Brannex",
  "species": [],
  "partners": [],
  "powers": [],
  "powersText": "Ability to mimic superhuman abilities",
  "image": {
    "url": "https://upload.wikimedia.org/wikipedia/commons/thumb/1/1c/Wiki_letter_w_cropped.svg/20px-Wiki_letter_w_cropped.svg.png",
    "width": "20",
    "height": "14"
  },
  "pageviews": 4714
}
