{
  "aliases": [
    "Swarm"
  ],
  "alliances": [
    "Exterminators"
  ],
  "authors": [
    "Bill Mantlo",
    "John Byrne"
  ],
  "description": "Fritz von Meyer was once a Nazi scientist, the details of which remain unrevealed, although it is known he had access to looted gold from countless European capitals to fund his research.",
  "image": "http://i.annihil.us/u/prod/marvel/i/mg/8/50/4c0030df47ab2/standard_xlarge.jpg",
  "isHero": false,
  "isVillain": false,
  "name": "Swarm",
  "partners": [
  ],
  "powers": [
    "Intangibility",
    "Ability to mentally manipulate the bees that compose his body",
    "Shapeshifting",
    "Flight"
  ],
  "ranking": {
    "comicCount": 1,
    "eventCount": 0,
    "pageviewCount": 3000,
    "pageviewRank": -1,
    "serieCount": 1,
    "storyCount": 1
  },
  "secretIdentities": [
    "Fritz von Meyer"
  ],
  "species": [
  ],
  "urls": {
    "marvel": "http://marvel.com/characters/2272/swarm",
    "wikipedia": "https://en.wikipedia.org/wiki/Swarm_(comics)"
  }
}