{
  "name": "Thor",
  "url": "https://en.wikipedia.org/wiki/Thor_(Marvel_Comics)",
  "realName": null,
  "creators": [
    "Stan Lee",
    "Larry Lieber",
    "Jack Kirby"
  ],
  "teams": [
    "Avengers",
    "Warriors Three",
    "God Squad",
    "Avengers Unity Squad"
  ],
  "aliases": "Siegmund, Siegfried, Dr. Donald Blake, Jake Olson, Sigurd Jarlson, Eric Masterson , Odinson",
  "species": [],
  "partners": [],
  "powers": [
    "Superhuman strength",
    "endurance",
    "longevity",
    "Mjolnir",
    "Dimensional transportation",
    "Electric manipulation",
    "Flight",
    "Weather manipulation"
  ],
  "powersText": [
    "Superhuman strengthendurance",
    "and longevity",
    "Abilities via Mjolnir:",
    "Dimensional transportation",
    "Electric manipulation",
    "Flight",
    "Weather manipulation"
  ],
  "image": {
    "url": "https://upload.wikimedia.org/wikipedia/en/thumb/4/41/Thor-272.jpg/250px-Thor-272.jpg",
    "width": "250",
    "height": "386"
  },
  "pageviews": 101536
}
