{
  "aliases": [
    "Mary Walker",
    "Typhoid",
    "Walker",
    "Bloody Mary",
    "Mutant Zero",
    "Innocent Mary",
    "Mary Mezinis",
    "Virgin Mary",
    "Lyla Hughes",
    "Siryn",
    "Typhoid Mary"
  ],
  "authors": [
    "John Romita, Jr.",
    "Ann Nocenti"
  ],
  "description": "Typhoid Mary, an enemy and former lover of Daredevil with psionic powers, including telekinesis, is also truly gravely mentally ill and not entirely responsible for her actions.",
  "image": "http://i.annihil.us/u/prod/marvel/i/mg/1/f0/4c00390aa2403/standard_xlarge.jpg",
  "isHero": false,
  "isVillain": false,
  "name": "Typhoid Mary",
  "partners": [
    "Kingpin"
  ],
  "powers": [
    "Pyrokinesis",
    "Arsenal of bladed weapons",
    "Limited mind control",
    "Telekinesis",
    "Peak-level agility",
    "Reflexes",
    "Exceptional swordswoman",
    "Trained martial artist",
    "Excellent physical condition",
    "Enhanced strength",
    "Highly skilled athlete"
  ],
  "ranking": {
    "comicCount": 25,
    "eventCount": 1,
    "pageviewCount": 11788,
    "pageviewRank": -1,
    "serieCount": 12,
    "storyCount": 26
  },
  "secretIdentities": [
    "Mary Walker"
  ],
  "species": [
    "Mutant"
  ],
  "teams": [
    "Brotherhood of Mutants",
    "The Hand",
    "Avengers: The Initiative",
    "Woman's Action Movement",
    "The Initiative",
    "Hand",
    "Shadow Initiative",
    "Sisterhood of Mutants"
  ],
  "urls": {
    "marvel": "http://marvel.com/characters/2893/typhoid_mary",
    "wikipedia": "https://en.wikipedia.org/wiki/Typhoid_Mary_(comics)"
  }
}