{
  "name": "Ultimo",
  "url": "https://en.wikipedia.org/wiki/Ultimo_(Marvel_Comics)",
  "realName": "Ultimo",
  "creators": [
    "Stan Lee"
  ],
  "teams": [
    "Mandarin's Minions"
  ],
  "aliases": "The Living Holocaust, Doomsday Machine",
  "species": [],
  "partners": [],
  "powers": [],
  "powersText": [
    "Superhuman strength",
    "speed and durability",
    "Heat absorption",
    "Concussive force or disintegration beam projection via eyes",
    "Size manipulation",
    "Self-repair",
    "Ability to adapt his defenses"
  ],
  "image": {
    "url": "https://upload.wikimedia.org/wikipedia/en/b/be/Ultimo_%28robot%29.jpg",
    "width": "198",
    "height": "350"
  },
  "pageviews": 3250
}
