{
  "aliases": "",
  "creators": [
    "Joe Simon",
    "Jack Kirby"
  ],
  "image": {
    "height": "373",
    "url": "https://upload.wikimedia.org/wikipedia/en/thumb/3/3b/GoldenAgeVision.jpg/220px-GoldenAgeVision.jpg",
    "width": "220"
  },
  "name": "The Vision",
  "pageviews": 5768,
  "partners": [
  ],
  "powers": [
  ],
  "powersText": [
    "Flight",
    "Cold and ice generation",
    "Limited teleportation",
    "Generate illusory images of himself"
  ],
  "realName": "Aarkus",
  "species": [
  ],
  "teams": [
    "Invaders"
  ],
  "url": "https://en.wikipedia.org/wiki/Vision_(Timely_Comics)"
}