{
  "aliases": "",
  "creators": [
    "Brian Michael Bendis",
    "Alex Maleev"
  ],
  "image": {
    "height": "388",
    "url": "https://upload.wikimedia.org/wikipedia/en/thumb/6/64/WhiteTigerDT.jpg/250px-WhiteTigerDT.jpg",
    "width": "250"
  },
  "name": "White Tiger",
  "pageviews": 18741,
  "partners": [
    "Daredevil",
    "Iron Fist"
  ],
  "powers": [
  ],
  "powersText": [
    "Experienced unarmed combatant",
    "Trained investigator",
    "Expert markswoman",
    "Superhuman martial arts skills and slightly superhuman physical attributes via mystical amulets",
    "Camouflage"
  ],
  "realName": "Angela del Toro",
  "species": [
  ],
  "teams": [
    "The Hand",
    "FBI"
  ],
  "url": "https://en.wikipedia.org/wiki/White_Tiger_(Angela_del_Toro)"
}