{
  "aliases": "",
  "creators": [
    "Peter B. Gillis",
    "Brent Anderson"
  ],
  "image": {
    "height": "358",
    "url": "https://upload.wikimedia.org/wikipedia/en/2/2a/Wildcard_comics.jpg",
    "width": "250"
  },
  "name": "Wildcard",
  "pageviews": 348,
  "partners": [
  ],
  "powers": [
  ],
  "powersText": [
    "Power mimicry",
    "Enhanced strength"
  ],
  "realName": "John Crenella",
  "species": [
  ],
  "teams": [
    "Strikeforce: Morituri"
  ],
  "url": "https://en.wikipedia.org/wiki/Wildcard_(comics)"
}