{
  "aliases": [
    "Yeti"
  ],
  "authors": [
    "Stan Lee",
    "Jack Kirby"
  ],
  "description": "Yeti is the name of two fictional comic book characters from the Marvel Comics universe.",
  "isHero": false,
  "isVillain": false,
  "name": "Yeti",
  "partners": [
  ],
  "powers": [
  ],
  "ranking": {
    "comicCount": 0,
    "eventCount": 0,
    "pageviewCount": 711,
    "pageviewRank": -1,
    "serieCount": 0,
    "storyCount": 0
  },
  "secretIdentities": [
  ],
  "species": [
  ],
  "teams": [
    "Department K",
    "Weapon P.R.I.M.E.",
    "First Line"
  ],
  "urls": {
    "wikipedia": "https://en.wikipedia.org/wiki/Yeti_(comics)"
  }
}